docs2tops.py
docs2tops-0.0.3.dist-info/LICENSE.txt
docs2tops-0.0.3.dist-info/METADATA
docs2tops-0.0.3.dist-info/WHEEL
docs2tops-0.0.3.dist-info/top_level.txt
docs2tops-0.0.3.dist-info/RECORD
