Metadata-Version: 2.1
Name: docs2tops
Version: 0.0.3
Summary: Takes a list of documents and returns fully automated & labeled dictionaries where topic names are keys and semantically similar keywords from the documents as values
Home-page: https://github.com/orkhan-amrullayev/docs2tops
Author: Orkhan Amrullayev
Author-email: orkhan_amrullayev@gmail.com
Keywords: nlp topic modelling text clustering
Classifier: Programming Language :: Python
Classifier: Intended Audience :: Science/Research
Classifier: Intended Audience :: Developers
Classifier: Topic :: Scientific/Engineering :: Artificial Intelligence
Classifier: License :: OSI Approved :: MIT License
Classifier: Topic :: Scientific/Engineering
Classifier: Operating System :: Microsoft :: Windows
Classifier: Operating System :: POSIX
Classifier: Operating System :: Unix
Classifier: Operating System :: MacOS
Classifier: Programming Language :: Python :: 3.9
License-File: LICENSE.txt
Requires-Dist: pandas (~=1.5.3)
Requires-Dist: numpy (~=1.23)
Requires-Dist: nltk (~=3.8.1)
Requires-Dist: tqdm
Requires-Dist: keybert (~=0.7.0)
Requires-Dist: keyphrase-vectorizers (~=0.0.11)
Requires-Dist: sentence-transformers (~=2.2.2)
Requires-Dist: transformers (~=4.26.1)
Requires-Dist: spacy (==3.5.0)
Requires-Dist: sklearn
Provides-Extra: dev
Requires-Dist: pytest (>=3.8) ; extra == 'dev'
